{
  "project_info": {
    "project_number": "891315206544",
    "firebase_url": "https://cable-c58c7.firebaseio.com",
    "project_id": "cable-c58c7",
    "storage_bucket": "cable-c58c7.appspot.com"
  },
  "client": [
    {
      "client_info": {
        "mobilesdk_app_id": "1:891315206544:android:59d86db15ceb538f25db15",
        "android_client_info": {
          "package_name": "cable.social.app"
        }
      },
      "oauth_client": [
        {
          "client_id": "891315206544-kkfgvqgvktons1cbjt7mlq982dkd79me.apps.googleusercontent.com",
          "client_type": 1,
          "android_info": {
            "package_name": "cable.social.app",
            "certificate_hash": "ce1676a6d6608f67d1e99eeb4e330848127c8bc9"
          }
        },
        {
          "client_id": "891315206544-maiue25tdjirksou86odakd1cjpp9cqb.apps.googleusercontent.com",
          "client_type": 3
        }
      ],
      "api_key": [
        {
          "current_key": "AIzaSyBgNqiFKhdCX7D_xPcbjU33ApDD4SKLaB4"
        }
      ],
      "services": {
        "appinvite_service": {
          "other_platform_oauth_client": [
            {
              "client_id": "891315206544-maiue25tdjirksou86odakd1cjpp9cqb.apps.googleusercontent.com",
              "client_type": 3
            }
          ]
        }
      }
    }
  ],
  "configuration_version": "1"
}